tests/__init__.py
tests/arrow_dataset.py
tests/frcnn.py
tests/frcnn_test.py
tests/generic_test.py
tests/test_adapter_extract.py
tests/test_coco_extract.py
tests/test_docvqa_extract.py
tests/test_funsd_extract.py
tests/test_gqa_extract.py
tests/test_imageset.py
tests/test_model.py
tests/test_vl_transpose.py
tests/visualizer_test.py
vltk/Features.py
vltk/__init__.py
vltk/cli.py
vltk/commands.py
vltk/compat.py
vltk/configs.py
vltk/decorators.py
vltk/download.py
vltk/features.py
vltk/inspection.py
vltk/memory.py
vltk/metrics.py
vltk/scratch.py
vltk/vars.py
vltk/abc/__init__.py
vltk/abc/adapter.py
vltk/abc/checkpoint.py
vltk/abc/complex.py
vltk/abc/config.py
vltk/abc/extraction.py
vltk/abc/loop.py
vltk/abc/processor.py
vltk/abc/simple.py
vltk/abc/visnadapter.py
vltk/abc/visnlangadatper.py
vltk/adapters/__init__.py
vltk/adapters/clevr.py
vltk/adapters/clevrref.py
vltk/adapters/coco2014.py
vltk/adapters/cococaptions.py
vltk/adapters/docvqa.py
vltk/adapters/frcnn.py
vltk/adapters/funsd.py
vltk/adapters/gqa.py
vltk/adapters/vgqa.py
vltk/adapters/visualgenome.py
vltk/adapters/vqa.py
vltk/dataset/__init__.py
vltk/dataset/basedataset.py
vltk/dataset/builder.py
vltk/dataset/langdataset.py
vltk/dataset/loader.py
vltk/dataset/visndataset.py
vltk/dataset/visnlangdataset.py
vltk/legacy/__init__.py
vltk/legacy/coco2014.py
vltk/legacy/frcnn.py
vltk/legacy/gqa.py
vltk/legacy/legacy_train.py
vltk/legacy/processing.py
vltk/legacy/vit_ckp_convert.py
vltk/legacy/vqa.py
vltk/modeling/__init__.py
vltk/modeling/frcnn.py
vltk/modeling/configs/__init__.py
vltk/modeling/configs/frcnn.py
vltk/processing/__init__.py
vltk/processing/data.py
vltk/processing/image.py
vltk/processing/label.py
vltk/processing/lang.py
vltk/processing/optim.py
vltk/processing/sched.py
vltk/processing/visn.py
vltk/processing/visnlang.py
vltk/utils/__init__.py
vltk/utils/adapters.py
vltk/utils/base.py
vltk-1.0.4.dist-info/LICENSE
vltk-1.0.4.dist-info/METADATA
vltk-1.0.4.dist-info/WHEEL
vltk-1.0.4.dist-info/entry_points.txt
vltk-1.0.4.dist-info/top_level.txt
vltk-1.0.4.dist-info/RECORD
